Metadata-Version: 1.1
Name: densenlpt
Version: 0.0.5
Summary: `densenlpt` is a package for creating dictionary and vector from scentences & training model to predict.
Home-page: https://github.com/k-mawa/densenlpt
Author: Kosuke Mawatari
Author-email: UNKNOWN
License: MIT
Keywords: mecab,gensim,machine,machine learning,scikit-learn,sklearn,nlp,natto
Platform: UNKNOWN
Classifier: Programming Language :: Python :: 3
Classifier: Programming Language :: Python :: 3.3
Classifier: Programming Language :: Python :: 3.4
Classifier: License :: OSI Approved :: MIT License
